{"ID": 51116, "name": "Christian v. New York Department Of Labor", "href": "https://api.oyez.org/cases/1973/72-5704", "view_count": 0, "docket_number": "72-5704", "timeline": [{"event": "Argued", "dates": [122018400], "href": "https://api.oyez.org/case_timeline/case_timeline/31542"}, {"event": "Decided", "dates": [127976400], "href": "https://api.oyez.org/case_timeline/case_timeline/31543"}], "question": "", "citation": {"volume": "414", "page": "614", "year": "1974", "href": "https://api.oyez.org/case_citation/case_citation/15044"}, "term": "1973", "description": null, "justia_url": "https://supreme.justia.com/cases/federal/us/414/614/"}