{"ID": 55622, "name": "Holland v. Florida", "href": "https://api.oyez.org/cases/2009/09-5327", "view_count": 0, "docket_number": "09-5327", "timeline": [{"event": "Granted", "dates": [1255410000], "href": "https://api.oyez.org/case_timeline/case_timeline/40335"}, {"event": "Argued", "dates": [1267423200], "href": "https://api.oyez.org/case_timeline/case_timeline/40336"}, {"event": "Decided", "dates": [1276491600], "href": "https://api.oyez.org/case_timeline/case_timeline/40337"}], "question": "<p>Can \"gross negligence\" by counsel that directly results in the late filing of a petition for habeas corpus relief qualify as a circumstance warranting equitable tolling?</p>\n", "citation": {"volume": "560", "page": "631", "year": "2010", "href": "https://api.oyez.org/case_citation/case_citation/19545"}, "term": "2009", "description": "A case in which the Court held that a state prisoner who has exhausted their appeals process in their state has one year to file a writ of habeas corpus, with certain exceptions (including attorney misconduct) that may allow the courts to relax that deadline.", "justia_url": "https://supreme.justia.com/cases/federal/us/560/631/"}