{"ID": 51639, "name": "Mandel v. Bradley", "href": "https://api.oyez.org/cases/1976/76-128", "view_count": 0, "docket_number": "76-128", "timeline": [{"event": "Argued", "dates": [225525600], "href": "https://api.oyez.org/case_timeline/case_timeline/32481"}, {"event": "Decided", "dates": [235285200], "href": "https://api.oyez.org/case_timeline/case_timeline/32482"}], "question": "", "citation": {"volume": "432", "page": "173", "year": "1977", "href": "https://api.oyez.org/case_citation/case_citation/15567"}, "term": "1976", "description": null, "justia_url": "https://supreme.justia.com/cases/federal/us/432/173/"}