{"ID": 62433, "name": "Commonwealth of Massachusetts v. Mellon", "href": "https://api.oyez.org/cases/1900-1940/262us447", "view_count": 0, "docket_number": "24-orig", "timeline": [{"event": "Argued", "dates": [-1472670000, -1472583600], "href": "https://api.oyez.org/case_timeline/case_timeline/53024"}, {"event": "Decided", "dates": [-1469905200], "href": "https://api.oyez.org/case_timeline/case_timeline/53025"}], "question": "<p>Did the expenditure of funds under the Maternity Act of 1921 violate the Takings Clause of the Fifth Amendment?</p>\n", "citation": {"volume": "262", "page": "447", "year": "1923", "href": "https://api.oyez.org/case_citation/case_citation/27235"}, "term": "1900-1940", "description": null, "justia_url": "https://supreme.justia.com/cases/federal/us/262/447/"}