{"ID": 61844, "name": "Walz v. Tax Comm'n of the City of New York", "href": "https://api.oyez.org/cases/1969/135", "view_count": 0, "docket_number": "135", "timeline": [{"event": "Argued", "dates": [-3693600], "href": "https://api.oyez.org/case_timeline/case_timeline/51104"}, {"event": "Decided", "dates": [10645200], "href": "https://api.oyez.org/case_timeline/case_timeline/51105"}], "question": "<p>Did the property tax exemptions violate the Establishment Clause of the First Amendment?</p>\n", "citation": {"volume": "397", "page": "664", "year": "1970", "href": "https://api.oyez.org/case_citation/case_citation/26626"}, "term": "1969", "description": null, "justia_url": "https://supreme.justia.com/cases/federal/us/397/664/"}