{"ID": 62725, "name": "Life Technologies Corp. v. Promega Corp.", "href": "https://api.oyez.org/cases/2016/14-1538", "view_count": 0, "docket_number": "14-1538", "timeline": [{"event": "Granted", "dates": [1467003600], "href": "https://api.oyez.org/case_timeline/case_timeline/53841"}, {"event": "Argued", "dates": [1481004000], "href": "https://api.oyez.org/case_timeline/case_timeline/53922"}, {"event": "Decided", "dates": [1487743200], "href": "https://api.oyez.org/case_timeline/case_timeline/53974"}], "question": "<p>Does supplying a single component of a multi-component invention from the United States for sale abroad expose the manufacturer to liability for infringement based on worldwide sales?</p>\n", "citation": {"volume": "580", "page": null, "year": "2017", "href": "https://api.oyez.org/case_citation/case_citation/27439"}, "term": "2016", "description": "A case in which the Court held that supplying a single component of a multi-component invention from the United States for sale abroad does not expose the manufacturer to liability for infringement based on worldwide sales.", "justia_url": "https://supreme.justia.com/cases/federal/us/580/14-1538/"}