{"ID": 54074, "name": "Godinez v. Moran", "href": "https://api.oyez.org/cases/1992/92-725", "view_count": 0, "docket_number": "92-725", "timeline": [{"event": "Argued", "dates": [735368400], "href": "https://api.oyez.org/case_timeline/case_timeline/37001"}, {"event": "Decided", "dates": [740898000], "href": "https://api.oyez.org/case_timeline/case_timeline/37002"}, {"event": "Granted", "dates": [724312800], "href": "https://api.oyez.org/case_timeline/case_timeline/53622"}], "question": "<p>Does the Due Process Clause of the Fourteenth Amendment require a trial court to apply a heightened \"reasoned choice\" standard to determine the competency of a defendant to enter a plea of guilty or waive counsel?</p>\n", "citation": {"volume": "509", "page": "389", "year": "1993", "href": "https://api.oyez.org/case_citation/case_citation/18003"}, "term": "1992", "description": null, "justia_url": "https://supreme.justia.com/cases/federal/us/509/389/"}