{"ID": 51950, "name": "Edmonds v. Compagnie Generale Transatl.", "href": "https://api.oyez.org/cases/1978/78-479", "view_count": 0, "docket_number": "78-479", "timeline": [{"event": "Argued", "dates": [290671200], "href": "https://api.oyez.org/case_timeline/case_timeline/33035"}, {"event": "Decided", "dates": [299307600], "href": "https://api.oyez.org/case_timeline/case_timeline/33036"}], "question": "", "citation": {"volume": "443", "page": "256", "year": "1979", "href": "https://api.oyez.org/case_citation/case_citation/15878"}, "term": "1978", "description": null, "justia_url": "https://supreme.justia.com/cases/federal/us/443/256/"}