{"ID": 50756, "name": "Barker v. Wingo", "href": "https://api.oyez.org/cases/1971/71-5255", "view_count": 0, "docket_number": "71-5255", "timeline": [{"event": "Argued", "dates": [71820000], "href": "https://api.oyez.org/case_timeline/case_timeline/30883"}, {"event": "Decided", "dates": [78037200], "href": "https://api.oyez.org/case_timeline/case_timeline/30884"}, {"event": "Granted", "dates": [64476000], "href": "https://api.oyez.org/case_timeline/case_timeline/53596"}], "question": "<p> Can the right to a speedy trial be implicitly waived?</p>\n", "citation": {"volume": "407", "page": "514", "year": "1972", "href": "https://api.oyez.org/case_citation/case_citation/14684"}, "term": "1971", "description": null, "justia_url": "https://supreme.justia.com/cases/federal/us/407/514/"}