{"ID": 60069, "name": "Maynard v. Durham & Southern Railway Company", "href": "https://api.oyez.org/cases/1960/183", "view_count": 0, "docket_number": "183", "timeline": [{"event": "Argued", "dates": [-283024800], "href": "https://api.oyez.org/case_timeline/case_timeline/48298"}, {"event": "Decided", "dates": [-279655200], "href": "https://api.oyez.org/case_timeline/case_timeline/48299"}], "question": "", "citation": {"volume": "365", "page": "160", "year": "1961", "href": "https://api.oyez.org/case_citation/case_citation/24851"}, "term": "1960", "description": null, "justia_url": "https://supreme.justia.com/cases/federal/us/365/160/"}