{"ID": 62055, "name": "Odom v. United States", "href": "https://api.oyez.org/cases/1970/300", "view_count": 0, "docket_number": "300", "timeline": [{"event": "Decided", "dates": [26978400], "href": "https://api.oyez.org/case_timeline/case_timeline/51456"}], "question": "", "citation": {"volume": "400", "page": "23", "year": "1970", "href": "https://api.oyez.org/case_citation/case_citation/26837"}, "term": "1970", "description": null, "justia_url": "https://supreme.justia.com/cases/federal/us/400/23/"}