{"ID": 52039, "name": "Wolston v. Reader's Digest Association, Inc.", "href": "https://api.oyez.org/cases/1978/78-5414", "view_count": 0, "docket_number": "78-5414", "timeline": [{"event": "Argued", "dates": [293176800], "href": "https://api.oyez.org/case_timeline/case_timeline/33190"}, {"event": "Decided", "dates": [299221200], "href": "https://api.oyez.org/case_timeline/case_timeline/33191"}, {"event": "Granted", "dates": [284623200], "href": "https://api.oyez.org/case_timeline/case_timeline/53535"}], "question": "<p>Is Wolston a public figure and required to prove actual malice in order to win a libel suit?</p>\n", "citation": {"volume": "443", "page": "157", "year": "1979", "href": "https://api.oyez.org/case_citation/case_citation/15967"}, "term": "1978", "description": null, "justia_url": "https://supreme.justia.com/cases/federal/us/443/157/"}