{"ID": 59873, "name": "Commissioner of Internal Revenue v. Acker", "href": "https://api.oyez.org/cases/1959/13", "view_count": 0, "docket_number": "13", "timeline": [{"event": "Argued", "dates": [-321994800], "href": "https://api.oyez.org/case_timeline/case_timeline/47968"}, {"event": "Decided", "dates": [-319572000], "href": "https://api.oyez.org/case_timeline/case_timeline/47969"}], "question": "", "citation": {"volume": "361", "page": "87", "year": "1959", "href": "https://api.oyez.org/case_citation/case_citation/24655"}, "term": "1959", "description": null, "justia_url": "https://supreme.justia.com/cases/federal/us/361/87/"}