{"ID": 55283, "name": "Miller-El v. Dretke", "href": "https://api.oyez.org/cases/2004/03-9659", "view_count": 0, "docket_number": "03-9659", "timeline": [{"event": "Granted", "dates": [1088398800], "href": "https://api.oyez.org/case_timeline/case_timeline/39410"}, {"event": "Argued", "dates": [1102312800], "href": "https://api.oyez.org/case_timeline/case_timeline/39411"}, {"event": "Decided", "dates": [1118638800], "href": "https://api.oyez.org/case_timeline/case_timeline/39412"}], "question": "<ol>\n<li>Did the Fifth Circuit Court of Appeals, by rejecting Miller-El's claim the prosecution purposefully excluded blacks from his jury, violate the U.S. Supreme Court's decision in Miller-El v. Cockrell (2003)? 2. Did the Texas jury selection manual encourage unconstitutional disparate questioning based on race?</li>\n</ol>\n", "citation": {"volume": "545", "page": "", "year": "2005", "href": "https://api.oyez.org/case_citation/case_citation/20546"}, "term": "2004", "description": null, "justia_url": null}