{"ID": 56127, "name": "Lopez v. Smith", "href": "https://api.oyez.org/cases/2014/13-946", "view_count": 0, "docket_number": "13-946", "timeline": [{"event": "Granted", "dates": [1412571600], "href": "https://api.oyez.org/case_timeline/case_timeline/41724"}, {"event": "Decided", "dates": [1412571600], "href": "https://api.oyez.org/case_timeline/case_timeline/41725"}], "question": "<p>Did the U.S. Court of Appeals for the Ninth Circuit properly apply its own precedent in determining that Smith's habeas petition should be granted?</p>\n", "citation": {"volume": "574", "page": "1", "year": "2014", "href": "https://api.oyez.org/case_citation/case_citation/20928"}, "term": "2014", "description": "A case in which the Court ruled that the U.S. Court of Appeals for the Ninth Circuit improperly applied its own precedent to create a habeas relief rule more specific than the rule established by Supreme Court decision.", "justia_url": "https://supreme.justia.com/cases/federal/us/574/1/"}