{"ID": 60934, "name": "Angelet v. Fay", "href": "https://api.oyez.org/cases/1964/578", "view_count": 0, "docket_number": "578", "timeline": [{"event": "Argued", "dates": [-151783200], "href": "https://api.oyez.org/case_timeline/case_timeline/49730"}, {"event": "Decided", "dates": [-144183600], "href": "https://api.oyez.org/case_timeline/case_timeline/49731"}], "question": "", "citation": {"volume": "381", "page": "654", "year": "1965", "href": "https://api.oyez.org/case_citation/case_citation/25716"}, "term": "1964", "description": null, "justia_url": "https://supreme.justia.com/cases/federal/us/381/654/"}