{"ID": 54875, "name": "Buckman Company v. Plaintiffs' Legal Committee", "href": "https://api.oyez.org/cases/2000/98-1768", "view_count": 0, "docket_number": "98-1768", "timeline": [{"event": "Argued", "dates": [975909600], "href": "https://api.oyez.org/case_timeline/case_timeline/38493"}, {"event": "Decided", "dates": [982735200], "href": "https://api.oyez.org/case_timeline/case_timeline/38494"}], "question": "<p>Does the Federal Food, Drug, and Cosmetic Act, as amended by the Medical Device Amendments of 1976, pre-empt civil actions related to the alleged fraudulent approval of orthopedic bone screw devices?</p>\n", "citation": {"volume": "531", "page": "341", "year": "2001", "href": "https://api.oyez.org/case_citation/case_citation/18804"}, "term": "2000", "description": null, "justia_url": "https://supreme.justia.com/cases/federal/us/531/341/"}