{"ID": 55797, "name": "Brown v. Entertainment Merchants Association", "href": "https://api.oyez.org/cases/2010/08-1448", "view_count": 0, "docket_number": "08-1448", "timeline": [{"event": "Granted", "dates": [1272258000], "href": "https://api.oyez.org/case_timeline/case_timeline/40781"}, {"event": "Argued", "dates": [1288674000], "href": "https://api.oyez.org/case_timeline/case_timeline/40782"}, {"event": "Decided", "dates": [1309150800], "href": "https://api.oyez.org/case_timeline/case_timeline/40783"}], "question": "<p>Does the First Amendment bar a state from restricting the sale of violent video games to minors?</p>\n", "citation": {"volume": "564", "page": null, "year": "2011", "href": "https://api.oyez.org/case_citation/case_citation/19719"}, "term": "2010", "description": "A case in which the Court held that video games, including violent ones, are protected speech under the First Amendment.", "justia_url": "https://supreme.justia.com/cases/federal/us/564/786/"}