{"ID": 62811, "name": "Bristol-Myers Squibb Co. v. Superior Court of California", "href": "https://api.oyez.org/cases/2016/16-466", "view_count": 0, "docket_number": "16-466", "timeline": [{"event": "Granted", "dates": [1484805600], "href": "https://api.oyez.org/case_timeline/case_timeline/53969"}, {"event": "Argued", "dates": [1493096400], "href": "https://api.oyez.org/case_timeline/case_timeline/54028"}, {"event": "Decided", "dates": [1497848400], "href": "https://api.oyez.org/case_timeline/case_timeline/54060"}], "question": "<p>Do a plaintiff\u2019s claims sufficiently arise out of or relate to a defendant\u2019s forum activities to create specific jurisdiction when the plaintiff\u2019s claims would be exactly the same even if the defendant had no forum contacts?</p>\n", "citation": {"volume": "582", "page": null, "year": "2017", "href": "https://api.oyez.org/case_citation/case_citation/27505"}, "term": "2016", "description": "A case in which the Court determined that, when the plaintiffs\u2019 claims would have been exactly the same even if the defendant had no forum state contacts, there is no basis for specific jurisdiction because the case does not sufficiently arise out of or relate to the defendant\u2019s forum activities.", "justia_url": "https://supreme.justia.com/cases/federal/us/582/16-466/"}