{"ID": 50605, "name": "McNeil v. Director, Patuxent Institution", "href": "https://api.oyez.org/cases/1971/71-5144", "view_count": 0, "docket_number": "71-5144", "timeline": [{"event": "Argued", "dates": [72597600], "href": "https://api.oyez.org/case_timeline/case_timeline/30622"}, {"event": "Decided", "dates": [77778000], "href": "https://api.oyez.org/case_timeline/case_timeline/30623"}], "question": "", "citation": {"volume": "407", "page": "245", "year": "1972", "href": "https://api.oyez.org/case_citation/case_citation/14533"}, "term": "1971", "description": null, "justia_url": "https://supreme.justia.com/cases/federal/us/407/245/"}