{"ID": 55611, "name": "Knowles v. Mirzayance", "href": "https://api.oyez.org/cases/2008/07-1315", "view_count": 0, "docket_number": "07-1315", "timeline": [{"event": "Granted", "dates": [1214542800], "href": "https://api.oyez.org/case_timeline/case_timeline/40306"}, {"event": "Argued", "dates": [1231826400], "href": "https://api.oyez.org/case_timeline/case_timeline/40307"}, {"event": "Decided", "dates": [1237870800], "href": "https://api.oyez.org/case_timeline/case_timeline/40308"}], "question": "<p>1) Did the Ninth Circuit exceed it authority by granting habeas corpus relief without considering whether state court adjudication of Mr. Mirzayance's claim was \"unreasonable\" under 28 U.S.C. Section 2254(d)?</p>\n<p>2) May a federal appellate court substitute factual findings of the district court without determining whether the district court's findings were \"clearly erroneous?\"</p>\n", "citation": {"volume": "556", "page": null, "year": "2009", "href": "https://api.oyez.org/case_citation/case_citation/20793"}, "term": "2008", "description": "A case in which the Court found that in order to find counsel ineffective, the defendant must show both \"deficient performance\" and \"prejudice.\"", "justia_url": null}