{"ID": 51747, "name": "United States v. LaSalle National Bank", "href": "https://api.oyez.org/cases/1977/77-365", "view_count": 0, "docket_number": "77-365", "timeline": [{"event": "Argued", "dates": [259999200], "href": "https://api.oyez.org/case_timeline/case_timeline/32671"}, {"event": "Decided", "dates": [267080400], "href": "https://api.oyez.org/case_timeline/case_timeline/32672"}], "question": null, "citation": {"volume": "437", "page": "298", "year": "1978", "href": "https://api.oyez.org/case_citation/case_citation/15675"}, "term": "1977", "description": null, "justia_url": "https://supreme.justia.com/cases/federal/us/437/298/"}