{"ID": 54901, "name": "Shafer v. S. Carolina", "href": "https://api.oyez.org/cases/2000/00-5250", "view_count": 0, "docket_number": "00-5250", "timeline": [{"event": "Argued", "dates": [979020000], "href": "https://api.oyez.org/case_timeline/case_timeline/38543"}, {"event": "Decided", "dates": [985068000], "href": "https://api.oyez.org/case_timeline/case_timeline/38544"}], "question": "<p>Did the South Carolina Supreme Court properly hold Simmons v. South Carolina inapplicable to the state's current sentencing regime?</p>\n", "citation": {"volume": "532", "page": "36", "year": "2001", "href": "https://api.oyez.org/case_citation/case_citation/18830"}, "term": "2000", "description": null, "justia_url": "https://supreme.justia.com/cases/federal/us/532/36/"}