{"ID": 61135, "name": "Davis v. North Carolina", "href": "https://api.oyez.org/cases/1965/815", "view_count": 0, "docket_number": "815", "timeline": [{"event": "Argued", "dates": [-116103600], "href": "https://api.oyez.org/case_timeline/case_timeline/50054"}, {"event": "Decided", "dates": [-111524400], "href": "https://api.oyez.org/case_timeline/case_timeline/50055"}], "question": "", "citation": {"volume": "384", "page": "737", "year": "1966", "href": "https://api.oyez.org/case_citation/case_citation/25917"}, "term": "1965", "description": null, "justia_url": "https://supreme.justia.com/cases/federal/us/384/737/"}