{"ID": 55733, "name": "Bobby v. Mitts", "href": "https://api.oyez.org/cases/2010/10-1000", "view_count": 0, "docket_number": "10-1000", "timeline": [{"event": "Granted", "dates": [1304312400], "href": "https://api.oyez.org/case_timeline/case_timeline/40619"}, {"event": "Decided", "dates": [1304312400], "href": "https://api.oyez.org/case_timeline/case_timeline/40620"}], "question": "<p>Were the jury instructions given at the penalty phase of the murder trial contrary to clearly established law for purposes of the Antiterrorism and Effective Death Penalty Act?</p>\n", "citation": {"volume": "563", "page": "395", "year": "2011", "href": "https://api.oyez.org/case_citation/case_citation/19655"}, "term": "2010", "description": "A case in which the Court held that the jury instructions given at the penalty phase of the murder trial were not contrary to clearly established law for purposes of the Antiterrorism and Effective Death Penalty Act.", "justia_url": "https://supreme.justia.com/cases/federal/us/563/395/"}