{"ID": 62789, "name": "Howell v. Howell", "href": "https://api.oyez.org/cases/2016/15-1031", "view_count": 0, "docket_number": "15-1031", "timeline": [{"event": "Granted", "dates": [1480658400], "href": "https://api.oyez.org/case_timeline/case_timeline/53941"}, {"event": "Argued", "dates": [1489986000], "href": "https://api.oyez.org/case_timeline/case_timeline/53989"}, {"event": "Decided", "dates": [1494824400], "href": "https://api.oyez.org/case_timeline/case_timeline/54035"}], "question": "<p>Does the Uniformed Services Former Spouses\u2019 Protection Act preempt a state court\u2019s order directing a veteran to pay a former spouse that spouse\u2019s full portion of the veteran\u2019s military retirement pay despite a reduction, when that reduction results from the veteran\u2019s post-divorce waiver of retirement pay in order to receive compensation for a service-connected disability?</p>\n", "citation": {"volume": "581", "page": null, "year": "2017", "href": "https://api.oyez.org/case_citation/case_citation/27489"}, "term": "2016", "description": "A case in which the Court determined that the Uniformed Services Former Spouses\u2019 Protection Act prevents state courts from treating the waived portion of military retirement pay as a divisible community asset for the purpose of divorce proceedings.", "justia_url": "https://supreme.justia.com/cases/federal/us/581/15-1031/"}