{"ID": 50825, "name": "Sloan v. Lemon", "href": "https://api.oyez.org/cases/1972/72-459", "view_count": 0, "docket_number": "72-459", "timeline": [{"event": "Argued", "dates": [103788000], "href": "https://api.oyez.org/case_timeline/case_timeline/31011"}, {"event": "Decided", "dates": [109832400], "href": "https://api.oyez.org/case_timeline/case_timeline/31012"}], "question": "", "citation": {"volume": "413", "page": "825", "year": "1973", "href": "https://api.oyez.org/case_citation/case_citation/14753"}, "term": "1972", "description": null, "justia_url": "https://supreme.justia.com/cases/federal/us/413/825/"}