{"ID": 51191, "name": "Serfass v. United States", "href": "https://api.oyez.org/cases/1974/73-1424", "view_count": 0, "docket_number": "73-1424", "timeline": [{"event": "Argued", "dates": [155800800], "href": "https://api.oyez.org/case_timeline/case_timeline/31680"}, {"event": "Decided", "dates": [163054800], "href": "https://api.oyez.org/case_timeline/case_timeline/31681"}], "question": "", "citation": {"volume": "420", "page": "377", "year": "1975", "href": "https://api.oyez.org/case_citation/case_citation/15119"}, "term": "1974", "description": null, "justia_url": "https://supreme.justia.com/cases/federal/us/420/377/"}