{"ID": 53600, "name": "Massachusetts v. Morash", "href": "https://api.oyez.org/cases/1988/88-32", "view_count": 0, "docket_number": "88-32", "timeline": [{"event": "Argued", "dates": [604044000], "href": "https://api.oyez.org/case_timeline/case_timeline/36093"}, {"event": "Decided", "dates": [608878800], "href": "https://api.oyez.org/case_timeline/case_timeline/36094"}, {"event": "Granted", "dates": [591858000], "href": "https://api.oyez.org/case_timeline/case_timeline/53341"}], "question": "<p>(1) Does a company\u2019s policy of paying its discharged employees for their unused vacation time constitute an employee welfare benefit plan within the meaning of the Employee Retirement Income Security Act of 1974 (ERISA)?</p>\n<p>(2) Does ERISA\u2019s broad pre-emption provision foreclose a criminal action to enforce that policy?</p>\n<p>\u00a0</p>\n", "citation": {"volume": "490", "page": "107", "year": "1989", "href": "https://api.oyez.org/case_citation/case_citation/17529"}, "term": "1988", "description": "A case in which the Court concluded that an employee\u2019s unused vacation time does not constitute an employee welfare benefit plan under the Employment Retirement Income Security Act of 1974. ", "justia_url": "https://supreme.justia.com/cases/federal/us/490/107/"}