{"ID": 55188, "name": "Iowa v. Tovar", "href": "https://api.oyez.org/cases/2003/02-1541", "view_count": 0, "docket_number": "02-1541", "timeline": [{"event": "Granted", "dates": [1064898000], "href": "https://api.oyez.org/case_timeline/case_timeline/39143"}, {"event": "Argued", "dates": [1074664800], "href": "https://api.oyez.org/case_timeline/case_timeline/39144"}, {"event": "Decided", "dates": [1078725600], "href": "https://api.oyez.org/case_timeline/case_timeline/39145"}], "question": "<p>Given the 6th Amendment's right to counsel, to what extent must a defendant be informed of the consequences of pleading guilty while waiving the right to an attorney?</p>\n", "citation": {"volume": "541", "page": "77", "year": "2004", "href": "https://api.oyez.org/case_citation/case_citation/19116"}, "term": "2003", "description": null, "justia_url": "https://supreme.justia.com/cases/federal/us/541/77/"}