{"ID": 61214, "name": "Fleischmann Distilling Corporation v. Maier Brewing Company", "href": "https://api.oyez.org/cases/1966/214", "view_count": 0, "docket_number": "214", "timeline": [{"event": "Argued", "dates": [-90871200], "href": "https://api.oyez.org/case_timeline/case_timeline/50157"}, {"event": "Decided", "dates": [-83703600], "href": "https://api.oyez.org/case_timeline/case_timeline/50158"}], "question": "", "citation": {"volume": "386", "page": "714", "year": "1967", "href": "https://api.oyez.org/case_citation/case_citation/25996"}, "term": "1966", "description": null, "justia_url": "https://supreme.justia.com/cases/federal/us/386/714/"}