{"ID": 62427, "name": "Stafford v. Wallace", "href": "https://api.oyez.org/cases/1900-1940/258us495", "view_count": 0, "docket_number": "687", "timeline": [{"event": "Argued", "dates": [-1508004000, -1507917600], "href": "https://api.oyez.org/case_timeline/case_timeline/53012"}, {"event": "Decided", "dates": [-1504378800], "href": "https://api.oyez.org/case_timeline/case_timeline/53013"}], "question": "<p>Did Congress have authority under the Commerce Clause to pass and enforce the Packers and Stockyards Act of 1921?</p>\n", "citation": {"volume": "258", "page": "495", "year": "1922", "href": "https://api.oyez.org/case_citation/case_citation/27229"}, "term": "1900-1940", "description": null, "justia_url": "https://supreme.justia.com/cases/federal/us/258/495/"}