{"ID": 54070, "name": "United States v. California", "href": "https://api.oyez.org/cases/1992/91-2003", "view_count": 0, "docket_number": "91-2003", "timeline": [{"event": "Argued", "dates": [730447200], "href": "https://api.oyez.org/case_timeline/case_timeline/36993"}, {"event": "Decided", "dates": [735800400], "href": "https://api.oyez.org/case_timeline/case_timeline/36994"}], "question": "<p>May the United States Government receive compensation for the state of California's allegedly unfounded taxation of a private federal contractor?</p>\n", "citation": {"volume": "507", "page": "746", "year": "1993", "href": "https://api.oyez.org/case_citation/case_citation/17999"}, "term": "1992", "description": null, "justia_url": "https://supreme.justia.com/cases/federal/us/507/746/"}