{"ID": 55299, "name": "eBay Inc. v. MercExchange, L.L.C.", "href": "https://api.oyez.org/cases/2005/05-130", "view_count": 0, "docket_number": "05-130", "timeline": [{"event": "Granted", "dates": [1133157600], "href": "https://api.oyez.org/case_timeline/case_timeline/39452"}, {"event": "Argued", "dates": [1143612000], "href": "https://api.oyez.org/case_timeline/case_timeline/39453"}, {"event": "Decided", "dates": [1147669200], "href": "https://api.oyez.org/case_timeline/case_timeline/39454"}], "question": "<p>Under the Patent Act, should a permanent injunction always be issued when a patent has been violated, absent exceptional circumstances?</p>\n", "citation": {"volume": "547", "page": "388", "year": "2006", "href": "https://api.oyez.org/case_citation/case_citation/20627"}, "term": "2005", "description": null, "justia_url": "https://supreme.justia.com/cases/federal/us/547/388/"}