{"ID": 52079, "name": "Chiarella v. United States", "href": "https://api.oyez.org/cases/1979/78-1202", "view_count": 0, "docket_number": "78-1202", "timeline": [{"event": "Argued", "dates": [310629600], "href": "https://api.oyez.org/case_timeline/case_timeline/33265"}, {"event": "Decided", "dates": [322207200], "href": "https://api.oyez.org/case_timeline/case_timeline/33266"}], "question": "<p>Did Chiarella violate Section 10(b) of the 1934 Act by failing to disclose the impending takeover before trading in the target company's securities?</p>\n", "citation": {"volume": "445", "page": "222", "year": "1980", "href": "https://api.oyez.org/case_citation/case_citation/16007"}, "term": "1979", "description": null, "justia_url": "https://supreme.justia.com/cases/federal/us/445/222/"}