{"ID": 55600, "name": "Montejo v. Louisiana", "href": "https://api.oyez.org/cases/2008/07-1529", "view_count": 0, "docket_number": "07-1529", "timeline": [{"event": "Argued", "dates": [1231826400], "href": "https://api.oyez.org/case_timeline/case_timeline/40274"}, {"event": "Decided", "dates": [1243314000], "href": "https://api.oyez.org/case_timeline/case_timeline/40275"}], "question": "<p>After the appointment of an attorney, does a defendant need to take additional steps to accept the appointment in order to secure the protections afforded by the Sixth Amendment?</p>\n", "citation": {"volume": "556", "page": "778", "year": "2009", "href": "https://api.oyez.org/case_citation/case_citation/19523"}, "term": "2008", "description": "A case in which the Court held that after the appointment of an attorney, a defendant does not necessarily need to take additional steps to accept the appointment in order to secure the protections of the Sixth Amendment.", "justia_url": "https://supreme.justia.com/cases/federal/us/556/778/"}