{"ID": 60440, "name": "Schneider v. Rusk", "href": "https://api.oyez.org/cases/1962/251", "view_count": 0, "docket_number": "251", "timeline": [{"event": "Decided", "dates": [-216756000], "href": "https://api.oyez.org/case_timeline/case_timeline/48926"}], "question": "", "citation": {"volume": "372", "page": "224", "year": "1963", "href": "https://api.oyez.org/case_citation/case_citation/25222"}, "term": "1962", "description": null, "justia_url": "https://supreme.justia.com/cases/federal/us/372/224/"}