{"ID": 61459, "name": "Katz v. United States", "href": "https://api.oyez.org/cases/1967/35", "view_count": 0, "docket_number": "35", "timeline": [{"event": "Argued", "dates": [-69706800], "href": "https://api.oyez.org/case_timeline/case_timeline/50524"}, {"event": "Decided", "dates": [-64346400], "href": "https://api.oyez.org/case_timeline/case_timeline/50525"}], "question": "<p>Does the Fourth Amendment protection against unreasonable searches and seizures require the police to obtain a search warrant in order to wiretap a public pay phone?</p>\n", "citation": {"volume": "389", "page": "347", "year": "1967", "href": "https://api.oyez.org/case_citation/case_citation/26241"}, "term": "1967", "description": "A case in which the Court found that the government putting a tap on a public payphone is a violation of the users' Fourth Amendment rights.", "justia_url": "https://supreme.justia.com/cases/federal/us/389/347/"}