{"ID": 55204, "name": "Tory v. Cochran", "href": "https://api.oyez.org/cases/2004/03-1488", "view_count": 0, "docket_number": "03-1488", "timeline": [{"event": "Granted", "dates": [1096347600], "href": "https://api.oyez.org/case_timeline/case_timeline/39188"}, {"event": "Argued", "dates": [1111471200], "href": "https://api.oyez.org/case_timeline/case_timeline/39189"}, {"event": "Decided", "dates": [1117515600], "href": "https://api.oyez.org/case_timeline/case_timeline/39190"}], "question": "<p>Did a judge's order that someone stop making defaming statements about a public figure, even after that figure's death, violate the First Amendment right to free speech?</p>\n", "citation": {"volume": "544", "page": "734", "year": "2005", "href": "https://api.oyez.org/case_citation/case_citation/19132"}, "term": "2004", "description": null, "justia_url": "https://supreme.justia.com/cases/federal/us/544/734/"}