{"ID": 60464, "name": "Gastelum-Quinones v. Kennedy", "href": "https://api.oyez.org/cases/1962/39", "view_count": 0, "docket_number": "39", "timeline": [{"event": "Argued", "dates": [-214250400], "href": "https://api.oyez.org/case_timeline/case_timeline/48966"}, {"event": "Decided", "dates": [-206478000], "href": "https://api.oyez.org/case_timeline/case_timeline/48967"}], "question": "", "citation": {"volume": "374", "page": "469", "year": "1963", "href": "https://api.oyez.org/case_citation/case_citation/25246"}, "term": "1962", "description": null, "justia_url": "https://supreme.justia.com/cases/federal/us/374/469/"}