{"ID": 55708, "name": "City of Ontario v. Quon", "href": "https://api.oyez.org/cases/2009/08-1332", "view_count": 0, "docket_number": "08-1332", "timeline": [{"event": "Granted", "dates": [1260770400], "href": "https://api.oyez.org/case_timeline/case_timeline/40554"}, {"event": "Argued", "dates": [1271653200], "href": "https://api.oyez.org/case_timeline/case_timeline/40555"}, {"event": "Decided", "dates": [1276750800], "href": "https://api.oyez.org/case_timeline/case_timeline/40556"}], "question": "<p>1) Does a city employee have a reasonable expectation of privacy in text messages transmitted on his city-issued pager when the police department has no official privacy policy for the pagers?</p>\n<p>2) Did the Ninth Circuit contravene Supreme Court precedent by analyzing whether the police department could have used \"less intrusive methods\" of reviewing text messages?</p>\n", "citation": {"volume": "560", "page": "746", "year": "2010", "href": "https://api.oyez.org/case_citation/case_citation/19630"}, "term": "2009", "description": "A case in which the Court held that the city of Ontario's search of an employee's text messages did not violate his First Amendment rights because the search was not excessive in scope and was motivated by a legitimate work-related purpose.", "justia_url": "https://supreme.justia.com/cases/federal/us/560/746/"}