{"ID": 55055, "name": "Grutter v. Bollinger", "href": "https://api.oyez.org/cases/2002/02-241", "view_count": 0, "docket_number": "02-241", "timeline": [{"event": "Argued", "dates": [1049176800], "href": "https://api.oyez.org/case_timeline/case_timeline/38835"}, {"event": "Decided", "dates": [1056344400], "href": "https://api.oyez.org/case_timeline/case_timeline/38836"}], "question": "<p>Does the University of Michigan Law School's use of racial preferences in student admissions violate the Equal Protection Clause of the Fourteenth Amendment or Title VI of the Civil Rights Act of 1964?</p>\n", "citation": {"volume": "539", "page": "306", "year": "2003", "href": "https://api.oyez.org/case_citation/case_citation/18984"}, "term": "2002", "description": "A case in which the Court held that the use of race in the University of Michigan's Law School admissions decisions did not violate the Equal Protection Clause of the Fourteenth Amendment.", "justia_url": "https://supreme.justia.com/cases/federal/us/539/306/"}