{"ID": 55626, "name": "Bloate v. United States", "href": "https://api.oyez.org/cases/2009/08-728", "view_count": 0, "docket_number": "08-728", "timeline": [{"event": "Granted", "dates": [1240203600], "href": "https://api.oyez.org/case_timeline/case_timeline/40347"}, {"event": "Argued", "dates": [1254805200], "href": "https://api.oyez.org/case_timeline/case_timeline/40348"}, {"event": "Decided", "dates": [1268028000], "href": "https://api.oyez.org/case_timeline/case_timeline/40349"}], "question": "<p>Is time granted to prepare pretrial motions automatically excludable under 18 U.S.C. Section 3161(h)(1)?</p>\n", "citation": {"volume": "559", "page": "196", "year": "2010", "href": "https://api.oyez.org/case_citation/case_citation/19549"}, "term": "2009", "description": "A case in which the Court held that the time granted to prepare pretrial motions is not automatically granted exclusion from the Speedy Trial Act's 70-day time limit.", "justia_url": "https://supreme.justia.com/cases/federal/us/559/196/"}