{"ID": 61425, "name": "Bohannan v. Arizona ex rel. Smith", "href": "https://api.oyez.org/cases/1967/204", "view_count": 0, "docket_number": "204", "timeline": [{"event": "Decided", "dates": [-70398000], "href": "https://api.oyez.org/case_timeline/case_timeline/50466"}], "question": "", "citation": {"volume": "389", "page": "1", "year": "1967", "href": "https://api.oyez.org/case_citation/case_citation/26207"}, "term": "1967", "description": null, "justia_url": "https://supreme.justia.com/cases/federal/us/389/1/"}