{"ID": 54656, "name": "National Credit Union Administration v. First National Bank & Trust Company", "href": "https://api.oyez.org/cases/1997/96-843", "view_count": 0, "docket_number": "96-843", "timeline": [{"event": "Argued", "dates": [876114000], "href": "https://api.oyez.org/case_timeline/case_timeline/38088"}, {"event": "Decided", "dates": [888386400], "href": "https://api.oyez.org/case_timeline/case_timeline/38089"}], "question": "<p>Do banks and professional associations have standing under the Administrative Procedure Act to seek federal-court review of the National Credit Union Administration's decisions? Is the NCUA's interpretation of section 109 of the Federal Credit Union Act permissible?</p>\n", "citation": {"volume": "522", "page": "479", "year": "1998", "href": "https://api.oyez.org/case_citation/case_citation/18585"}, "term": "1997", "description": null, "justia_url": "https://supreme.justia.com/cases/federal/us/522/479/"}